LICENSE
ensure/__init__.py
ensure/py.typed
python_ensure-0.0.1.dist-info/LICENSE
python_ensure-0.0.1.dist-info/METADATA
python_ensure-0.0.1.dist-info/WHEEL
python_ensure-0.0.1.dist-info/RECORD
