Metadata-Version: 2.1
Name: python-ensure
Version: 0.0.1
Summary: Python functions used to ensure something.
Home-page: https://github.com/ChenyangGao/python-modules/tree/main/python-ensure
License: MIT
Keywords: ensure
Author: ChenyangGao
Author-email: wosiwujm@gmail.com
Requires-Python: >=3.12,<4.0
Classifier: Development Status :: 5 - Production/Stable
Classifier: Intended Audience :: Developers
Classifier: License :: OSI Approved :: MIT License
Classifier: Operating System :: OS Independent
Classifier: Programming Language :: Python
Classifier: Programming Language :: Python :: 3
Classifier: Programming Language :: Python :: 3.12
Classifier: Programming Language :: Python :: 3.13
Classifier: Programming Language :: Python :: 3 :: Only
Classifier: Topic :: Software Development
Classifier: Topic :: Software Development :: Libraries
Classifier: Topic :: Software Development :: Libraries :: Python Modules
Requires-Dist: integer_tool (>=0.0.5)
Project-URL: Repository, https://github.com/ChenyangGao/python-modules/tree/main/python-ensure
